pdf_sanitizer_diacde/__init__.py
pdf_sanitizer_diacde-1.3.3.dist-info/METADATA
pdf_sanitizer_diacde-1.3.3.dist-info/WHEEL
pdf_sanitizer_diacde-1.3.3.dist-info/top_level.txt
pdf_sanitizer_diacde-1.3.3.dist-info/RECORD
