Metadata-Version: 2.1
Name: pdf_sanitizer_diacde
Version: 1.3.3
Author: DIACDE - TJGO
License: Attribution-NonCommercial-ShareAlike
Requires-Python: >=3.9.4
